pulumi_volcenginecc/__init__.py
pulumi_volcenginecc/_inputs.py
pulumi_volcenginecc/_utilities.py
pulumi_volcenginecc/provider.py
pulumi_volcenginecc/pulumi-plugin.json
pulumi_volcenginecc/py.typed
pulumi_volcenginecc/alb/__init__.py
pulumi_volcenginecc/alb/_inputs.py
pulumi_volcenginecc/alb/acl.py
pulumi_volcenginecc/alb/certificate.py
pulumi_volcenginecc/alb/get_acl.py
pulumi_volcenginecc/alb/get_acls.py
pulumi_volcenginecc/alb/get_certificate.py
pulumi_volcenginecc/alb/get_certificates.py
pulumi_volcenginecc/alb/get_listener.py
pulumi_volcenginecc/alb/get_listeners.py
pulumi_volcenginecc/alb/get_load_balancer.py
pulumi_volcenginecc/alb/get_load_balancers.py
pulumi_volcenginecc/alb/get_server_group.py
pulumi_volcenginecc/alb/get_server_groups.py
pulumi_volcenginecc/alb/listener.py
pulumi_volcenginecc/alb/load_balancer.py
pulumi_volcenginecc/alb/outputs.py
pulumi_volcenginecc/alb/server_group.py
pulumi_volcenginecc/apig/__init__.py
pulumi_volcenginecc/apig/_inputs.py
pulumi_volcenginecc/apig/custom_domain.py
pulumi_volcenginecc/apig/gateway.py
pulumi_volcenginecc/apig/gateway_service.py
pulumi_volcenginecc/apig/get_custom_domain.py
pulumi_volcenginecc/apig/get_custom_domains.py
pulumi_volcenginecc/apig/get_gateway.py
pulumi_volcenginecc/apig/get_gateway_service.py
pulumi_volcenginecc/apig/get_gateway_services.py
pulumi_volcenginecc/apig/get_gateways.py
pulumi_volcenginecc/apig/get_upstream.py
pulumi_volcenginecc/apig/get_upstream_source.py
pulumi_volcenginecc/apig/get_upstream_sources.py
pulumi_volcenginecc/apig/get_upstreams.py
pulumi_volcenginecc/apig/outputs.py
pulumi_volcenginecc/apig/upstream.py
pulumi_volcenginecc/apig/upstream_source.py
pulumi_volcenginecc/ark/__init__.py
pulumi_volcenginecc/ark/_inputs.py
pulumi_volcenginecc/ark/endpoint.py
pulumi_volcenginecc/ark/get_endpoint.py
pulumi_volcenginecc/ark/get_endpoints.py
pulumi_volcenginecc/ark/outputs.py
pulumi_volcenginecc/autoscaling/__init__.py
pulumi_volcenginecc/autoscaling/_inputs.py
pulumi_volcenginecc-0.0.20.dist-info/METADATA
pulumi_volcenginecc-0.0.20.dist-info/WHEEL
pulumi_volcenginecc-0.0.20.dist-info/top_level.txt
pulumi_volcenginecc-0.0.20.dist-info/RECORD
